LICENSE
README.md
setup.py
wconfig/__init__.py
wconfig/features/Config.py
wconfig/features/VAR.py
wconfig/features/__init__.py
wconfig/static/T.py
wconfig/static/__init__.py
wconfig/utils/__init__.py
wconfig/utils/get_path.py
wconfig/utils/is_class.py
wconfig/utils/is_dataclass.py
wconfig/utils/lead.py
whaox_wconfig.egg-info/PKG-INFO
whaox_wconfig.egg-info/SOURCES.txt
whaox_wconfig.egg-info/dependency_links.txt
whaox_wconfig.egg-info/requires.txt
whaox_wconfig.egg-info/top_level.txt