Metadata-Version: 2.1
Name: whaox-wconfig
Version: 1.0.3
Summary: Library to simplify working with the environment
Home-page: https://github.com/topanim/WApi
Author: WHAOX
Author-email: gorogannisan641@gmail.com
License: MIT LICENSE, see LICENSE file
Keywords: python,env,environment,config
License-File: LICENSE
Requires-Dist: python-dotenv
